telegrambot/__init__.py
telegrambot/bot.py
telegrambot/error.py
telegrambot/message.py
telegrambot/parser.py
tinkoff_backend_academy_telegram_bot-0.0.7.dist-info/LICENSE
tinkoff_backend_academy_telegram_bot-0.0.7.dist-info/METADATA
tinkoff_backend_academy_telegram_bot-0.0.7.dist-info/WHEEL
tinkoff_backend_academy_telegram_bot-0.0.7.dist-info/top_level.txt
tinkoff_backend_academy_telegram_bot-0.0.7.dist-info/RECORD
